.gitignore
LICENSE.txt
MANIFEST.in
README.md
setup.py
cmsplugin_iconlist/__init__.py
cmsplugin_iconlist/cms_plugins.py
cmsplugin_iconlist/models.py
cmsplugin_iconlist.egg-info/PKG-INFO
cmsplugin_iconlist.egg-info/SOURCES.txt
cmsplugin_iconlist.egg-info/dependency_links.txt
cmsplugin_iconlist.egg-info/requires.txt
cmsplugin_iconlist.egg-info/top_level.txt
cmsplugin_iconlist/locale/locale/de/LC_MESSAGES/django.mo
cmsplugin_iconlist/locale/locale/de/LC_MESSAGES/django.po
cmsplugin_iconlist/migrations/0001_initial.py
cmsplugin_iconlist/migrations/__init__.py
cmsplugin_iconlist/migrations_django/0001_initial.py
cmsplugin_iconlist/migrations_django/__init__.py
cmsplugin_iconlist/static/cmsplugin_iconlist/css/font-awesome.min.css
cmsplugin_iconlist/static/cmsplugin_iconlist/css/style.css
cmsplugin_iconlist/static/cmsplugin_iconlist/fonts/FontAwesome.otf
cmsplugin_iconlist/static/cmsplugin_iconlist/fonts/fontawesome-webfont.eot
cmsplugin_iconlist/static/cmsplugin_iconlist/fonts/fontawesome-webfont.svg
cmsplugin_iconlist/static/cmsplugin_iconlist/fonts/fontawesome-webfont.ttf
cmsplugin_iconlist/static/cmsplugin_iconlist/fonts/fontawesome-webfont.woff
cmsplugin_iconlist/templates/cmsplugin_iconlist/_iconlist_plugin.html