Metadata-Version: 1.1
Name: cmsplugin-iconlist
Version: 0.0.1
Summary: A djangocms plugin displaying a list of font awesome icons
Home-page: https://github.com/creimers/cmsplugin_iconlist
Author: Christoph Reimers
Author-email: christoph@superservice-international.com
License: BSD License
Keywords: djangocms,django,font awesome
Platform: UNKNOWN
Classifier: Operating System :: OS Independent
Classifier: Development Status :: 4 - Beta
Classifier: Programming Language :: Python
Classifier: Framework :: Django
Classifier: Programming Language :: Python :: 2.7
Classifier: Programming Language :: Python :: 3.4
